pysolaredge/__init__.py
pysolaredge/crypto.py
pysolaredge/decoder.py
pysolaredge/exceptions.py
pysolaredge/peewee.py
pysolaredge/utils.py
pysolaredge/devices/__init__.py
pysolaredge/devices/battery.py
pysolaredge/devices/devicebase.py
pysolaredge/devices/event.py
pysolaredge/devices/inverter1ph.py
pysolaredge/devices/inverter3ph.py
pysolaredge/devices/meter.py
pysolaredge/devices/oldoptimizer.py
pysolaredge/devices/optimizer.py
pysolaredge-0.5.5.dist-info/DESCRIPTION.rst
pysolaredge-0.5.5.dist-info/METADATA
pysolaredge-0.5.5.dist-info/RECORD
pysolaredge-0.5.5.dist-info/WHEEL
pysolaredge-0.5.5.dist-info/metadata.json
pysolaredge-0.5.5.dist-info/top_level.txt
