Metadata-Version: 2.0
Name: pysolaredge
Version: 0.5.5
Summary: Library for decrypting and decoding messages from SolarEdge inverters
Home-page: https://github.com/tinuzz/python-solaredge
Author: Martijn Grendelman
Author-email: m@rtijn.net
License: UNKNOWN
Platform: UNKNOWN
Classifier: Programming Language :: Python :: 3 :: Only
Classifier: License :: OSI Approved :: Apache Software License
Classifier: Operating System :: OS Independent
Requires-Dist: pycrypto
